[{"colour":"red","time":[2017,11,27,22,8,26],"number":1},{"colour":"red","time":[2017,11,27,22,28,50],"number":2},{"colour":"red","time":[2017,11,27,22,35,36],"number":3},{"colour":"red","time":[2017,11,27,22,37,23],"number":4},{"colour":"red","time":[2017,11,27,22,41,33],"number":5},{"colour":"green","time":[2017,11,27,22,44,48],"number":6},{"colour":"green","time":[2017,11,27,22,46,27],"number":7},{"colour":"green","time":[2017,11,27,22,46,59],"number":8},{"colour":"green","time":[2017,11,27,22,52,11],"number":9},{"colour":"amber","time":[2017,11,27,22,53,3],"number":10},{"colour":"green","time":[2017,11,27,22,55,6],"number":11},{"colour":"amber","time":[2017,11,27,22,55,37],"number":12},{"colour":"amber","time":[2017,11,27,22,56,17],"number":13},{"colour":"green","time":[2017,11,27,23,3,37],"number":14},{"colour":"amber","time":[2017,11,27,23,5,42],"number":15},{"colour":"amber","time":[2017,11,27,23,10,48],"number":16},{"colour":"amber","time":[2017,11,27,23,11,25],"number":17},{"colour":"red","time":[2017,11,27,23,12,18],"number":18},{"colour":"green","time":[2017,11,27,23,13,36],"number":19},{"colour":"red","time":[2017,11,27,23,14,24],"number":20},{"colour":"amber","time":[2017,11,27,23,19,15],"number":21},{"colour":"red","time":[2017,11,27,23,21,20],"number":22},{"colour":"red","time":[2017,11,27,23,21,40],"number":23},{"colour":"red","time":[2017,11,27,23,39,21],"number":24},{"colour":"red","time":[2017,11,27,23,40,37],"number":25},{"colour":"red","time":[2017,11,27,23,42,24],"number":26},{"colour":"red","time":[2017,11,27,23,45,7],"number":27},{"colour":"green","time":[2017,11,27,23,46,5],"number":28},{"colour":"green","time":[2017,11,27,23,47,15],"number":29},{"colour":"amber","time":[2017,11,27,23,51,47],"number":30},{"colour":"amber","time":[2017,11,27,23,52,8],"number":31},{"colour":"red","time":[2017,11,27,23,52,37],"number":32},{"colour":"amber","time":[2017,11,27,23,54,18],"number":33},{"colour":"red","time":[2017,11,27,23,54,45],"number":34},{"colour":"red","time":[2017,11,27,23,55,21],"number":35},{"colour":"amber","time":[2017,11,27,23,57,35],"number":36},{"colour":"green","time":[2017,11,27,23,59,6],"number":37},{"colour":"amber","time":[2017,11,28,0,3,18],"number":38},{"colour":"red","time":[2017,11,28,0,3,48],"number":39},{"colour":"red","time":[2017,11,28,0,5,47],"number":40},{"colour":"red","time":[2017,11,28,0,6,52],"number":41},{"colour":"red","time":[2017,11,28,0,13,22],"number":42},{"colour":"red","time":[2017,11,28,0,16,0],"number":43},{"colour":"red","time":[2017,11,28,0,17,20],"number":44},{"colour":"red","time":[2017,11,28,0,18,26],"number":45},{"colour":"red","time":[2017,11,28,0,21,12],"number":46},{"colour":"amber","time":[2017,11,28,0,23,23],"number":47},{"colour":"amber","time":[2017,11,28,0,23,57],"number":48},{"colour":"amber","time":[2017,11,28,0,24,37],"number":49},{"colour":"red","time":[2017,11,28,0,25,27],"number":50},{"colour":"red","time":[2017,11,28,0,26,20],"number":51},{"colour":"red","time":[2017,11,28,0,31,56],"number":52},{"colour":"red","time":[2017,11,28,0,32,59],"number":53},{"colour":"red","time":[2017,11,28,0,33,19],"number":54},{"colour":"red","time":[2017,11,28,0,35,4],"number":55},{"colour":"green","time":[2017,11,28,0,36,43],"number":56},{"colour":"red","time":[2017,11,28,0,39,2],"number":57},{"colour":"amber","time":[2017,11,28,0,40,38],"number":58},{"colour":"red","time":[2017,11,28,0,40,55],"number":59},{"colour":"green","time":[2017,11,28,0,42,18],"number":60},{"colour":"green","time":[2017,11,28,0,42,54],"number":61},{"colour":"red","time":[2017,11,28,0,48,34],"number":62},{"colour":"red","time":[2017,11,28,0,59,24],"number":63},{"colour":"green","time":[2017,11,28,1,6,15],"number":64},{"colour":"green","time":[2017,11,28,1,7,6],"number":65},{"colour":"red","time":[2017,11,28,1,9,50],"number":66},{"colour":"red","time":[2017,11,28,1,11,39],"number":67},{"colour":"amber","time":[2017,11,28,1,14,2],"number":68},{"colour":"red","time":[2017,11,28,1,14,26],"number":69},{"colour":"green","time":[2017,11,28,1,14,45],"number":70},{"colour":"red","time":[2017,11,28,1,20,11],"number":71},{"colour":"amber","time":[2017,11,28,2,33,58],"number":72},{"colour":"amber","time":[2017,11,28,2,35,2],"number":73},{"colour":"green","time":[2017,11,28,2,35,38],"number":74},{"colour":"amber","time":[2017,11,28,2,40,9],"number":75},{"colour":"green","time":[2017,11,28,2,40,42],"number":76},{"colour":"green","time":[2017,11,28,2,43,58],"number":77},{"colour":"amber","time":[2017,11,28,2,44,52],"number":78},{"colour":"red","time":[2017,11,28,2,45,25],"number":79},{"colour":"amber","time":[2017,11,28,2,47,40],"number":80},{"colour":"amber","time":[2017,11,28,2,48,9],"number":81},{"colour":"amber","time":[2017,11,28,2,51,27],"number":82},{"colour":"amber","time":[2017,11,28,2,51,46],"number":83},{"colour":"timed_out","time":[2017,11,28,2,52,31],"number":84},{"colour":"timed_out","time":[2017,11,28,2,52,48],"number":85},{"colour":"timed_out","time":[2017,11,28,2,53,24],"number":86},{"colour":"timed_out","time":[2017,11,28,2,54,34],"number":87},{"colour":"green","time":[2017,11,28,2,55,18],"number":88},{"colour":"green","time":[2017,11,28,2,56,21],"number":89},{"colour":"green","time":[2017,11,28,2,59,23],"number":90},{"colour":"green","time":[2017,11,28,3,2,23],"number":91},{"colour":"green","time":[2017,11,28,3,7,24],"number":92},{"colour":"green","time":[2017,11,28,3,10,12],"number":93},{"colour":"green","time":[2017,11,28,3,11,10],"number":94},{"colour":"green","time":[2017,11,28,3,14,20],"number":95},{"colour":"green","time":[2017,11,28,3,14,25],"number":96},{"colour":"green","time":[2017,11,28,3,21,34],"number":97},{"colour":"green","time":[2017,11,28,3,33,39],"number":98},{"colour":"timed_out","time":[2017,11,28,3,38,17],"number":99},{"colour":"green","time":[2017,11,28,3,38,39],"number":100},{"colour":"amber","time":[2017,11,28,3,43,59],"number":101},{"colour":"amber","time":[2017,11,28,3,46,51],"number":102},{"colour":"amber","time":[2017,11,28,3,47,36],"number":103},{"colour":"amber","time":[2017,11,28,3,47,48],"number":104},{"colour":"green","time":[2017,11,28,3,48,17],"number":105},{"colour":"green","time":[2017,11,28,3,48,43],"number":106},{"colour":"green","time":[2017,11,28,3,49,33],"number":107},{"colour":"green","time":[2017,11,28,3,54,44],"number":108},{"colour":"green","time":[2017,11,28,3,55,9],"number":109},{"colour":"green","time":[2017,11,28,3,59,13],"number":110},{"colour":"green","time":[2017,11,28,4,10,57],"number":111},{"colour":"amber","time":[2017,11,28,4,13,32],"number":112},{"colour":"green","time":[2017,11,28,4,14,14],"number":113}]